ioLabs.py
psyscopex.py
hid/__init__.py
hid/cparser.py
hid/osx.py
hid/win32.py
ioLabs-3.2.dist-info/LICENSE
ioLabs-3.2.dist-info/METADATA
ioLabs-3.2.dist-info/WHEEL
ioLabs-3.2.dist-info/top_level.txt
ioLabs-3.2.dist-info/RECORD
