Metadata-Version: 2.1
Name: ioLabs
Version: 3.2
Summary: ioLab response box library
Home-page: http://www.ioLab.co.uk/
Author: John Montgomery
Author-email: UNKNOWN
License: BSD-3
Platform: UNKNOWN
Classifier: Development Status :: 4 - Beta
Classifier: Operating System :: MacOS :: MacOS X
Classifier: Operating System :: Microsoft :: Windows
Classifier: Programming Language :: Python
